{
  "version": 1,
  "acceptedAt": "2026-05-13T08:14:25.530Z",
  "corpus": [
    {
      "package": "@esbenwiberg/corpus-default",
      "version": "1.0.0"
    }
  ],
  "fitness": 83.24149659863947,
  "dimensions": {
    "context": 74.64285714285715,
    "consistency": 80,
    "cost": 86.66666666666667,
    "feedback": 74.89795918367346,
    "latency": null,
    "safety": 100
  },
  "probes": {
    "agent.guidance-present": 100,
    "agent.guidance-substance": 80,
    "arch.doc-present": 100,
    "changelog.strategy-declared": 100,
    "docs.contributing-present": 100,
    "docs.readme-present": 100,
    "docs.readme-substance": 50,
    "editorconfig.present": 100,
    "format.configured": 100,
    "hooks.precommit-present": 100,
    "lint.configured": 100,
    "safety.dangerous-script-flags": 100,
    "secrets.dotenv-gitignored": 100,
    "tests.runner-configured": 100,
    "types.configured": 100,
    "arch.fitness-tests-configured": 0,
    "ci.runs-tests": 100,
    "docs.adr-presence": 0,
    "gitignore.comprehensive": 100,
    "hooks.gates-lint-test-build": 0,
    "secrets.precommit-scan-configured": 100,
    "size.directory-depth": 80,
    "size.large-files": 100,
    "size.repo-token-estimate": 80,
    "specs.present": 0,
    "commits.conventional-followed": 100,
    "agent.guidance-quality": 80,
    "arch.boundaries-clear": 80,
    "arch.doc-quality": 50,
    "docs.adr-quality": null,
    "docs.readme-clarity": 80,
    "errors.actionability": 80,
    "runtime.dev-loop-bootable": 80,
    "specs.quality": null,
    "tests.cover-public-surface": 50
  },
  "commit": "82742f991b2c5ab5d6870970a251242ede371bce"
}
